pylobid/__init__.py
pylobid/pylobid.py
pylobid/utils.py
pylobid/validators.py
pylobid-3.0.0.dist-info/WHEEL
pylobid-3.0.0.dist-info/METADATA
pylobid-3.0.0.dist-info/RECORD
