Metadata-Version: 2.3
Name: pylobid
Version: 3.0.0
Summary: A lobid-REST-API client
Keywords: lobid
Author: Peter Andorfer, Christian Lölkes
Author-email: Peter Andorfer <p.andorfer@gmail.com>, Christian Lölkes <christian.loelkes@gmail.com>
License: MIT License
Requires-Dist: jsonpath-ng>=1.7.0
Requires-Dist: requests>=2.32.4
Requires-Python: >=3.8
Project-URL: Documentation, https://csae8092.github.io/pylobid/
Project-URL: Repository, https://github.com/csae8092/pylobid
